{"cameraMode":{"drawMode":0,"name":"Shaded","section":"Shading Mode"},"sceneLighting":true,"audioPlay":false,"sceneViewState":{"showFog":true,"showMaterialUpdate":false,"showSkybox":true,"showFlares":true,"showImageEffects":true,"showParticleSystems":true,"showVisualEffectGraphs":true,"m_FxEnabled":false},"in2DMode":false,"pivot":{"x":3.116792678833008,"y":7.596575736999512,"z":-26.222023010253908},"rotation":{"x":-0.07164149731397629,"y":0.9070426225662231,"z":-0.17178001999855042,"w":-0.37791892886161806},"size":18.161245346069337,"orthographic":true}